tmalibrarynew/__init__.py
tmalibrarynew/probes/__init__.py
tmalibrarynew/probes/communication.py
tmalibrarynew/probes/data.py
tmalibrarynew/probes/message.py
tmalibrarynew/probes/observation.py
tmalibrarynew-1.0.dist-info/LICENSE.txt
tmalibrarynew-1.0.dist-info/METADATA
tmalibrarynew-1.0.dist-info/WHEEL
tmalibrarynew-1.0.dist-info/top_level.txt
tmalibrarynew-1.0.dist-info/RECORD
