Metadata-Version: 2.1
Name: tmalibrarynew
Version: 1.0
Summary: Libraries to TMA
Home-page: https://github.com/eubr-atmosphere/tma-framework/tree/dev/common/common/tmalibrary
Author: Jorge Luiz
Author-email: jre-jl@hotmail.com
License: Apache 2.0
Platform: UNKNOWN
